{"links": {"self": {"href": "data/repositories/osrf/subt/issues/336/comments/55887580.json"}, "html": {"href": "#!/osrf/subt/issues/336#comment-55887580"}}, "issue": {"links": {"self": {"href": "data/repositories/osrf/subt/issues/336.json"}}, "type": "issue", "id": 336, "repository": {"links": {"self": {"href": "data/repositories/osrf/subt.json"}, "html": {"href": "#!/osrf/subt"}, "avatar": {"href": "data/bytebucket.org/ravatar/{3c95f6ad-c304-407c-b838-09597d836552}ts=2272898"}}, "type": "repository", "name": "subt", "full_name": "osrf/subt", "uuid": "{3c95f6ad-c304-407c-b838-09597d836552}"}, "title": "Handling /subt/finish for multiple robots"}, "content": {"raw": "`/subt/finish` is automatically called at the end of the run.  If you do not want to accidentally end the run early, don't call `/subt/finish` at all (this will terminate in a hour of simulation time then) or call `/subt/finish` whenever you would like to terminate the run early.\n\nThis issue is likely not a Blocker in the sense you can avoid calling `/subt/finish` altogether.  Having a consensus from the robots with regard to `/subt/finish` before terminating the CloudSim run might be a good feature for Cave Circuit.", "markup": "markdown", "html": "<p><code>/subt/finish</code> is automatically called at the end of the run.  If you do not want to accidentally end the run early, don't call <code>/subt/finish</code> at all (this will terminate in a hour of simulation time then) or call <code>/subt/finish</code> whenever you would like to terminate the run early.</p>\n<p>This issue is likely not a Blocker in the sense you can avoid calling <code>/subt/finish</code> altogether.  Having a consensus from the robots with regard to <code>/subt/finish</code> before terminating the CloudSim run might be a good feature for Cave Circuit.</p>", "type": "rendered"}, "created_on": "2020-01-27T13:40:38.834557+00:00", "user": {"display_name": "Arthur Schang", "uuid": "{1403972a-9b64-442b-a69c-d7e9557e1d87}", "links": {"self": {"href": "https://api.bitbucket.org/2.0/users/%7B1403972a-9b64-442b-a69c-d7e9557e1d87%7D"}, "html": {"href": "https://bitbucket.org/%7B1403972a-9b64-442b-a69c-d7e9557e1d87%7D/"}, "avatar": {"href": "https://avatar-management--avatars.us-west-2.prod.public.atl-paas.net/initials/AS-0.png"}}, "nickname": "Arthur Schang", "type": "user", "account_id": "557058:14b7fd50-d65a-47a8-825c-fa89681d07bd"}, "updated_on": "2020-01-27T13:41:02.444631+00:00", "type": "issue_comment", "id": 55887580}