{"links": {"self": {"href": "data/repositories/osrf/subt/issues/96/comments/52896476.json"}, "html": {"href": "#!/osrf/subt/issues/96#comment-52896476"}}, "issue": {"links": {"self": {"href": "data/repositories/osrf/subt/issues/96.json"}}, "type": "issue", "id": 96, "repository": {"links": {"self": {"href": "data/repositories/osrf/subt.json"}, "html": {"href": "#!/osrf/subt"}, "avatar": {"href": "data/bytebucket.org/ravatar/{3c95f6ad-c304-407c-b838-09597d836552}ts=2272898"}}, "type": "repository", "name": "subt", "full_name": "osrf/subt", "uuid": "{3c95f6ad-c304-407c-b838-09597d836552}"}, "title": "Having trouble with nvidia driver"}, "content": {"raw": "Thanks @{557058:155a32e2-420c-4d50-98e0-0e722f63f906} , your solution solved my issue. So I am able to run the simulation. But encountered new error,\n\n  \n\n`developer@baila-PC:~/subt_ws$ ign launch -v 4 competition.ign robotName1:=X1 robotConfig1:=X2_SENSOR_CONFIG_1`  \n\\[Dbg\\] \\[[Manager.cc:406](http://Manager.cc:406)\\] Forked a process for \\[ros\\] command\\[roslaunchsubt\\_roscompetition\\_init.launchworld\\_name:=tunnel\\_qual\\_ignvehicle\\_topics:=0\\]  \n\\[Dbg\\] \\[[Manager.cc:406](http://Manager.cc:406)\\] Forked a process for \\[x2\\_description\\] command\\[roslaunch--waitsubt\\_rosx2\\_description.launchworld\\_name:=tunnel\\_qual\\_ignname:=X1\\]  \n\\[Dbg\\] \\[[Manager.cc:406](http://Manager.cc:406)\\] Forked a process for \\[x2\\_ros\\_ign\\_bridge\\] command\\[roslaunch--waitsubt\\_rosvehicle\\_topics.launchworld\\_name:=tunnel\\_qual\\_ignname:=X1\\]  \n.\n\n.\n\n.  \n\nprocess\\[ros1\\_ign\\_bridge\\_baila\\_PC\\_499\\_3030296628978868002-2\\]: started with pid \\[567\\]  \n/opt/ros/melodic/lib/ros1\\_ign\\_bridge/parameter\\_bridge: symbol lookup error: /opt/ros/melodic/lib/ros1\\_ign\\_bridge/parameter\\_bridge: undefined symbol: \\_ZN8ignition4msgs8Odometry17default\\_instance\\_E  \n`[ros1_ign_bridge_baila_PC_499_3030296628978868002-2] process has died [pid 567, exit code 127, cmd /opt/ros/melodic/lib/ros1_ign_bridge/parameter_bridge /world/tunnel_qual_ign/clock@rosgraph_msgs/Clock@ignition.msgs.Clock /world/tunnel_qual_ign/clock:=/clock __name:=ros1_ign_bridge_baila_PC_499_3030296628978868002 __log:=/home/developer/.ros/log/54eb537c-a19f-11e9-a985-68a3c4a1e180/ros1_ign_bridge_baila_PC_499_3030296628978868002-2.log].`  \nlog file: /home/developer/.ros/log/54eb537c-a19f-11e9-a985-68a3c4a1e180/ros1\\_ign\\_bridge\\_baila\\_PC\\_499\\_3030296628978868002-2\\*.log  \nstarted roslaunch server [[http://baila-PC:44581/](http://baila-PC:44581/)](http://baila-PC:44581)\n\n# SUMMARY\n\nPARAMETERS\n\n* /X1/robot\\_description: <?xml version=\"1....\n* /rosdistro: melodic\n* /rosversion: 1.14.3\n\nNODES\n\nROS\\_MASTER\\_URI=[http://localhost:11311](http://localhost:11311)\n\nNo processes to monitor  \nshutting down processing monitor...  \n... shutting down processing monitor complete  \nprocess\\[X1/ros1\\_ign\\_bridge\\_imu-1\\]: started with pid \\[580\\]  \n/opt/ros/melodic/lib/ros1\\_ign\\_bridge/parameter\\_bridge: symbol lookup error: /opt/ros/melodic/lib/ros1\\_ign\\_bridge/parameter\\_bridge: undefined symbol: \\_ZN8ignition4msgs8Odometry17default\\_instance\\_E  \n`[X1/ros1_ign_bridge_imu-1] process has died [pid 580, exit code 127, cmd /opt/ros/melodic/lib/ros1_ign_bridge/parameter_bridge /world/tunnel_qual_ign/model/X1/link/base_link/sensor/imu_sensor/imu@sensor_msgs/Imu@ignition.msgs.IMU /world/tunnel_qual_ign/model/X1/link/base_link/sensor/imu_sensor/imu:=imu/data __name:=ros1_ign_bridge_imu __log:=/home/developer/.ros/log/54eb537c-a19f-11e9-a985-68a3c4a1e180/X1-ros1_ign_bridge_imu-1.log].`  \nlog file: /home/developer/.ros/log/54eb537c-a19f-11e9-a985-68a3c4a1e180/X1-ros1\\_ign\\_bridge\\_imu-1\\*.log  \n\\[Dbg\\] \\[[Manager.cc:295](http://Manager.cc:295)\\] Received signal\\[17\\]  \n\\[Dbg\\] \\[[Manager.cc:312](http://Manager.cc:312)\\] Death of process\\[500\\] with name\\[x2\\_description\\].  \nprocess\\[tf\\_world\\_static-3\\]: started with pid \\[584\\]  \nprocess\\[X1/ros1\\_ign\\_bridge\\_pose-2\\]: started with pid \\[603\\]  \n/opt/ros/melodic/lib/ros1\\_ign\\_bridge/parameter\\_bridge: symbol lookup error: /opt/ros/melodic/lib/ros1\\_ign\\_bridge/parameter\\_bridge: undefined symbol: \\_ZN8ignition4msgs8Odometry17default\\_instance\\_E  \n\\[X1/ros1\\_ign\\_bridge\\_pose-2\\] process has died \\[pid 603, exit code 127, cmd /opt/ros/melodic/lib/ros1\\_ign\\_bridge/parameter\\_bridge /model/X1/pose@geometry\\_msgs/TransformStamped@ignition.msgs.Pose /model/X1/pose:=pose \\_\\_name:=ros1\\_ign\\_bridge\\_pose \\_\\_log:=/home/developer/.ros/log/54eb537c-a19f-11e9-a985-68a3c4a1e180/X1-ros1\\_ign\\_bridge\\_pose-2.log\\].  \nlog file: /home/developer/.ros/log/54eb537c-a19f-11e9-a985-68a3c4a1e180/X1-ros1\\_ign\\_bridge\\_pose-2\\*.log  \nprocess\\[X1/ros1\\_ign\\_bridge\\_odom-3\\]: started with pid \\[609\\]  \n/opt/ros/melodic/lib/ros1\\_ign\\_bridge/parameter\\_bridge: symbol lookup error: /opt/ros/melodic/lib/ros1\\_ign\\_bridge/parameter\\_bridge: undefined symbol: \\_ZN8ignition4msgs8Odometry17default\\_instance\\_E  \n\\[X1/ros1\\_ign\\_bridge\\_odom-3\\] process has died \\[pid 609, exit code 127, cmd /opt/ros/melodic/lib/ros1\\_ign\\_bridge/parameter\\_bridge /model/X1/odometry@nav\\_msgs/Odometry@ignition.msgs.Odometry /model/X1/odometry:=odom \\_\\_name:=ros1\\_ign\\_bridge\\_odom \\_\\_log:=/home/developer/.ros/log/54eb537c-a19f-11e9-a985-68a3c4a1e180/X1-ros1\\_ign\\_bridge\\_odom-3.log\\].  \nlog file: /home/developer/.ros/log/54eb537c-a19f-11e9-a985-68a3c4a1e180/X1-ros1\\_ign\\_bridge\\_odom-3\\*.log  \nprocess\\[X1/ros1\\_ign\\_bridge\\_actuators-4\\]: started with pid \\[610\\]  \n/opt/ros/melodic/lib/ros1\\_ign\\_bridge/parameter\\_bridge: symbol lookup error: /opt/ros/melodic/lib/ros1\\_ign\\_bridge/parameter\\_bridge: undefined symbol: \\_ZN8ignition4msgs8Odometry17default\\_instance\\_E  \n\\[X1/ros1\\_ign\\_bridge\\_actuators-4\\] process has died \\[pid 610, exit code 127, cmd /opt/ros/melodic/lib/ros1\\_ign\\_bridge/parameter\\_bridge /model/X1/command/motor\\_speed@mav\\_msgs/Actuators@ignition.msgs.Actuators /model/X1/command/motor\\_speed:=command/motor\\_speed \\_\\_name:=ros1\\_ign\\_bridge\\_actuators \\_\\_log:=/home/developer/.ros/log/54eb537c-a19f-11e9-a985-68a3c4a1e180/X1-ros1\\_ign\\_bridge\\_actuators-4.log\\].  \nlog file: /home/developer/.ros/log/54eb537c-a19f-11e9-a985-68a3c4a1e180/X1-ros1\\_ign\\_bridge\\_actuators-4\\*.log  \nprocess\\[X1/ros1\\_ign\\_bridge\\_twist-5\\]: started with pid \\[611\\]  \n/opt/ros/melodic/lib/ros1\\_ign\\_bridge/parameter\\_bridge: symbol lookup error: /opt/ros/melodic/lib/ros1\\_ign\\_bridge/parameter\\_bridge: undefined symbol: \\_ZN8ignition4msgs8Odometry17default\\_instance\\_E  \n\\[X1/ros1\\_ign\\_bridge\\_twist-5\\] process has died \\[pid 611, exit code 127, cmd /opt/ros/melodic/lib/ros1\\_ign\\_bridge/parameter\\_bridge /model/X1/cmd\\_vel\\_relay@geometry\\_msgs/Twist@ignition.msgs.Twist /model/X1/cmd\\_vel\\_relay:=cmd\\_vel \\_\\_name:=ros1\\_ign\\_bridge\\_twist \\_\\_log:=/home/developer/.ros/log/54eb537c-a19f-11e9-a985-68a3c4a1e180/X1-ros1\\_ign\\_bridge\\_twist-5.log\\].  \nlog file: /home/developer/.ros/log/54eb537c-a19f-11e9-a985-68a3c4a1e180/X1-ros1\\_ign\\_bridge\\_twist-5\\*.log  \nprocess\\[X1/ros1\\_ign\\_bridge\\_camera-6\\]: started with pid \\[612\\]  \n/opt/ros/melodic/lib/ros1\\_ign\\_bridge/parameter\\_bridge: symbol lookup error: /opt/ros/melodic/lib/ros1\\_ign\\_bridge/parameter\\_bridge: undefined symbol: \\_ZN8ignition4msgs8Odometry17default\\_instance\\_E  \n\\[X1/ros1\\_ign\\_bridge\\_camera-6\\] process has died \\[pid 612, exit code 127, cmd /opt/ros/melodic/lib/ros1\\_ign\\_bridge/parameter\\_bridge /world/tunnel\\_qual\\_ign/model/X1/link/base\\_link/sensor/camera\\_front/image@sensor\\_msgs/Image@ignition.msgs.Image /world/tunnel\\_qual\\_ign/model/X1/link/base\\_link/sensor/camera\\_front/camera\\_info@sensor\\_msgs/CameraInfo@ignition.msgs.CameraInfo /world/tunnel\\_qual\\_ign/model/X1/link/base\\_link/sensor/camera\\_front/image:=front/image\\_raw /world/tunnel\\_qual\\_ign/model/X1/link/base\\_link/sensor/camera\\_front/camera\\_info:=front/camera\\_info \\_\\_name:=ros1\\_ign\\_bridge\\_camera \\_\\_log:=/home/developer/.ros/log/54eb537c-a19f-11e9-a985-68a3c4a1e180/X1-ros1\\_ign\\_bridge\\_camera-6.log\\].  \nlog file: /home/developer/.ros/log/54eb537c-a19f-11e9-a985-68a3c4a1e180/X1-ros1\\_ign\\_bridge\\_camera-6\\*.log  \nprocess\\[X1/ros1\\_ign\\_bridge\\_gpu\\_lidar-7\\]: started with pid \\[613\\]  \n/opt/ros/melodic/lib/ros1\\_ign\\_bridge/parameter\\_bridge: symbol lookup error: /opt/ros/melodic/lib/ros1\\_ign\\_bridge/parameter\\_bridge: undefined symbol: \\_ZN8ignition4msgs8Odometry17default\\_instance\\_E  \n\\[X1/ros1\\_ign\\_bridge\\_gpu\\_lidar-7\\] process has died \\[pid 613, exit code 127, cmd /opt/ros/melodic/lib/ros1\\_ign\\_bridge/parameter\\_bridge /world/tunnel\\_qual\\_ign/model/X1/link/base\\_link/sensor/front\\_laser/scan@sensor\\_msgs/LaserScan@ignition.msgs.LaserScan /world/tunnel\\_qual\\_ign/model/X1/link/base\\_link/sensor/front\\_laser/scan:=front\\_scan \\_\\_name:=ros1\\_ign\\_bridge\\_gpu\\_lidar \\_\\_log:=/home/developer/.ros/log/54eb537c-a19f-11e9-a985-68a3c4a1e180/X1-ros1\\_ign\\_bridge\\_gpu\\_lidar-7.log\\].  \nlog file: /home/developer/.ros/log/54eb537c-a19f-11e9-a985-68a3c4a1e180/X1-ros1\\_ign\\_bridge\\_gpu\\_lidar-7\\*.log  \nprocess\\[X1/ros1\\_ign\\_bridge\\_magnetometer-8\\]: started with pid \\[614\\]  \n/opt/ros/melodic/lib/ros1\\_ign\\_bridge/parameter\\_bridge: symbol lookup error: /opt/ros/melodic/lib/ros1\\_ign\\_bridge/parameter\\_bridge: undefined symbol: \\_ZN8ignition4msgs8Odometry17default\\_instance\\_E  \n\\[X1/ros1\\_ign\\_bridge\\_magnetometer-8\\] process has died \\[pid 614, exit code 127, cmd /opt/ros/melodic/lib/ros1\\_ign\\_bridge/parameter\\_bridge /world/tunnel\\_qual\\_ign/model/X1/link/base\\_link/sensor/magnetometer/magnetometer@sensor\\_msgs/MagneticField@ignition.msgs.Magnetometer /world/tunnel\\_qual\\_ign/model/X1/link/base\\_link/sensor/magnetometer/magnetometer:=magnetic\\_field \\_\\_name:=ros1\\_ign\\_bridge\\_magnetometer \\_\\_log:=/home/developer/.ros/log/54eb537c-a19f-11e9-a985-68a3c4a1e180/X1-ros1\\_ign\\_bridge\\_magnetometer-8.log\\].  \nlog file: /home/developer/.ros/log/54eb537c-a19f-11e9-a985-68a3c4a1e180/X1-ros1\\_ign\\_bridge\\_magnetometer-8\\*.log  \nprocess\\[X1/ros1\\_ign\\_bridge\\_fluid\\_pressure-9\\]: started with pid \\[615\\]  \n/opt/ros/melodic/lib/ros1\\_ign\\_bridge/parameter\\_bridge: symbol lookup error: /opt/ros/melodic/lib/ros1\\_ign\\_bridge/parameter\\_bridge: undefined symbol: \\_ZN8ignition4msgs8Odometry17default\\_instance\\_E  \n\\[X1/ros1\\_ign\\_bridge\\_fluid\\_pressure-9\\] process has died \\[pid 615, exit code 127, cmd /opt/ros/melodic/lib/ros1\\_ign\\_bridge/parameter\\_bridge /world/tunnel\\_qual\\_ign/model/X1/link/base\\_link/sensor/air\\_pressure/air\\_pressure@sensor\\_msgs/FluidPressure@ignition.msgs.FluidPressure /world/tunnel\\_qual\\_ign/model/X1/link/base\\_link/sensor/air\\_pressure/air\\_pressure:=air\\_pressure \\_\\_name:=ros1\\_ign\\_bridge\\_fluid\\_pressure \\_\\_log:=/home/developer/.ros/log/54eb537c-a19f-11e9-a985-68a3c4a1e180/X1-ros1\\_ign\\_bridge\\_fluid\\_pressure-9.log\\].  \nlog file: /home/developer/.ros/log/54eb537c-a19f-11e9-a985-68a3c4a1e180/X1-ros1\\_ign\\_bridge\\_fluid\\_pressure-9\\*.log  \nprocess\\[X1/pose\\_tf\\_broadcaster-10\\]: started with pid \\[616\\]\n\n  \n\nI have highlighted some of the lines. Those lines came in red and simulation came blank.   \n\n@{5cf75629ff02b50ea27b2817} , @{557058:095b1e12-74ed-4e20-b44f-2f0745b616e0}", "markup": "markdown", "html": "<p>Thanks <span class=\"ap-mention\" data-atlassian-id=\"557058:155a32e2-420c-4d50-98e0-0e722f63f906\">@Jose Luis Rivero</span> , your solution solved my issue. So I am able to run the simulation. But encountered new error,</p>\n<p><code>developer@baila-PC:~/subt_ws$ ign launch -v 4 competition.ign robotName1:=X1 robotConfig1:=X2_SENSOR_CONFIG_1</code><br />\n[Dbg] [<a data-is-external-link=\"true\" href=\"http://Manager.cc:406\" rel=\"nofollow\">Manager.cc:406</a>] Forked a process for [ros] command[roslaunchsubt_roscompetition_init.launchworld_name:=tunnel_qual_ignvehicle_topics:=0]<br />\n[Dbg] [<a data-is-external-link=\"true\" href=\"http://Manager.cc:406\" rel=\"nofollow\">Manager.cc:406</a>] Forked a process for [x2_description] command[roslaunch--waitsubt_rosx2_description.launchworld_name:=tunnel_qual_ignname:=X1]<br />\n[Dbg] [<a data-is-external-link=\"true\" href=\"http://Manager.cc:406\" rel=\"nofollow\">Manager.cc:406</a>] Forked a process for [x2_ros_ign_bridge] command[roslaunch--waitsubt_rosvehicle_topics.launchworld_name:=tunnel_qual_ignname:=X1]<br />\n.</p>\n<p>.</p>\n<p>.  </p>\n<p>process[ros1_ign_bridge_baila_PC_499_3030296628978868002-2]: started with pid [567]<br />\n/opt/ros/melodic/lib/ros1_ign_bridge/parameter_bridge: symbol lookup error: /opt/ros/melodic/lib/ros1_ign_bridge/parameter_bridge: undefined symbol: _ZN8ignition4msgs8Odometry17default_instance_E<br />\n<code>[ros1_ign_bridge_baila_PC_499_3030296628978868002-2] process has died [pid 567, exit code 127, cmd /opt/ros/melodic/lib/ros1_ign_bridge/parameter_bridge /world/tunnel_qual_ign/clock@rosgraph_msgs/Clock@ignition.msgs.Clock /world/tunnel_qual_ign/clock:=/clock __name:=ros1_ign_bridge_baila_PC_499_3030296628978868002 __log:=/home/developer/.ros/log/54eb537c-a19f-11e9-a985-68a3c4a1e180/ros1_ign_bridge_baila_PC_499_3030296628978868002-2.log].</code><br />\nlog file: /home/developer/.ros/log/54eb537c-a19f-11e9-a985-68a3c4a1e180/ros1_ign_bridge_baila_PC_499_3030296628978868002-2*.log<br />\nstarted roslaunch server <a data-is-external-link=\"true\" href=\"http://baila-PC:44581\" rel=\"nofollow\">[http://baila-PC:44581/](http://baila-PC:44581/)</a></p>\n<h1 id=\"markdown-header-summary\">SUMMARY</h1>\n<p>PARAMETERS</p>\n<ul>\n<li>/X1/robot_description: &lt;?xml version=\"1....</li>\n<li>/rosdistro: melodic</li>\n<li>/rosversion: 1.14.3</li>\n</ul>\n<p>NODES</p>\n<p>ROS_MASTER_URI=<a data-is-external-link=\"true\" href=\"http://localhost:11311\" rel=\"nofollow\">http://localhost:11311</a></p>\n<p>No processes to monitor<br />\nshutting down processing monitor...<br />\n... shutting down processing monitor complete<br />\nprocess[X1/ros1_ign_bridge_imu-1]: started with pid [580]<br />\n/opt/ros/melodic/lib/ros1_ign_bridge/parameter_bridge: symbol lookup error: /opt/ros/melodic/lib/ros1_ign_bridge/parameter_bridge: undefined symbol: _ZN8ignition4msgs8Odometry17default_instance_E<br />\n<code>[X1/ros1_ign_bridge_imu-1] process has died [pid 580, exit code 127, cmd /opt/ros/melodic/lib/ros1_ign_bridge/parameter_bridge /world/tunnel_qual_ign/model/X1/link/base_link/sensor/imu_sensor/imu@sensor_msgs/Imu@ignition.msgs.IMU /world/tunnel_qual_ign/model/X1/link/base_link/sensor/imu_sensor/imu:=imu/data __name:=ros1_ign_bridge_imu __log:=/home/developer/.ros/log/54eb537c-a19f-11e9-a985-68a3c4a1e180/X1-ros1_ign_bridge_imu-1.log].</code><br />\nlog file: /home/developer/.ros/log/54eb537c-a19f-11e9-a985-68a3c4a1e180/X1-ros1_ign_bridge_imu-1*.log<br />\n[Dbg] [<a data-is-external-link=\"true\" href=\"http://Manager.cc:295\" rel=\"nofollow\">Manager.cc:295</a>] Received signal[17]<br />\n[Dbg] [<a data-is-external-link=\"true\" href=\"http://Manager.cc:312\" rel=\"nofollow\">Manager.cc:312</a>] Death of process[500] with name[x2_description].<br />\nprocess[tf_world_static-3]: started with pid [584]<br />\nprocess[X1/ros1_ign_bridge_pose-2]: started with pid [603]<br />\n/opt/ros/melodic/lib/ros1_ign_bridge/parameter_bridge: symbol lookup error: /opt/ros/melodic/lib/ros1_ign_bridge/parameter_bridge: undefined symbol: _ZN8ignition4msgs8Odometry17default_instance_E<br />\n[X1/ros1_ign_bridge_pose-2] process has died [pid 603, exit code 127, cmd /opt/ros/melodic/lib/ros1_ign_bridge/parameter_bridge /model/X1/pose@geometry_msgs/TransformStamped@ignition.msgs.Pose /model/X1/pose:=pose __name:=ros1_ign_bridge_pose __log:=/home/developer/.ros/log/54eb537c-a19f-11e9-a985-68a3c4a1e180/X1-ros1_ign_bridge_pose-2.log].<br />\nlog file: /home/developer/.ros/log/54eb537c-a19f-11e9-a985-68a3c4a1e180/X1-ros1_ign_bridge_pose-2*.log<br />\nprocess[X1/ros1_ign_bridge_odom-3]: started with pid [609]<br />\n/opt/ros/melodic/lib/ros1_ign_bridge/parameter_bridge: symbol lookup error: /opt/ros/melodic/lib/ros1_ign_bridge/parameter_bridge: undefined symbol: _ZN8ignition4msgs8Odometry17default_instance_E<br />\n[X1/ros1_ign_bridge_odom-3] process has died [pid 609, exit code 127, cmd /opt/ros/melodic/lib/ros1_ign_bridge/parameter_bridge /model/X1/odometry@nav_msgs/Odometry@ignition.msgs.Odometry /model/X1/odometry:=odom __name:=ros1_ign_bridge_odom __log:=/home/developer/.ros/log/54eb537c-a19f-11e9-a985-68a3c4a1e180/X1-ros1_ign_bridge_odom-3.log].<br />\nlog file: /home/developer/.ros/log/54eb537c-a19f-11e9-a985-68a3c4a1e180/X1-ros1_ign_bridge_odom-3*.log<br />\nprocess[X1/ros1_ign_bridge_actuators-4]: started with pid [610]<br />\n/opt/ros/melodic/lib/ros1_ign_bridge/parameter_bridge: symbol lookup error: /opt/ros/melodic/lib/ros1_ign_bridge/parameter_bridge: undefined symbol: _ZN8ignition4msgs8Odometry17default_instance_E<br />\n[X1/ros1_ign_bridge_actuators-4] process has died [pid 610, exit code 127, cmd /opt/ros/melodic/lib/ros1_ign_bridge/parameter_bridge /model/X1/command/motor_speed@mav_msgs/Actuators@ignition.msgs.Actuators /model/X1/command/motor_speed:=command/motor_speed __name:=ros1_ign_bridge_actuators __log:=/home/developer/.ros/log/54eb537c-a19f-11e9-a985-68a3c4a1e180/X1-ros1_ign_bridge_actuators-4.log].<br />\nlog file: /home/developer/.ros/log/54eb537c-a19f-11e9-a985-68a3c4a1e180/X1-ros1_ign_bridge_actuators-4*.log<br />\nprocess[X1/ros1_ign_bridge_twist-5]: started with pid [611]<br />\n/opt/ros/melodic/lib/ros1_ign_bridge/parameter_bridge: symbol lookup error: /opt/ros/melodic/lib/ros1_ign_bridge/parameter_bridge: undefined symbol: _ZN8ignition4msgs8Odometry17default_instance_E<br />\n[X1/ros1_ign_bridge_twist-5] process has died [pid 611, exit code 127, cmd /opt/ros/melodic/lib/ros1_ign_bridge/parameter_bridge /model/X1/cmd_vel_relay@geometry_msgs/Twist@ignition.msgs.Twist /model/X1/cmd_vel_relay:=cmd_vel __name:=ros1_ign_bridge_twist __log:=/home/developer/.ros/log/54eb537c-a19f-11e9-a985-68a3c4a1e180/X1-ros1_ign_bridge_twist-5.log].<br />\nlog file: /home/developer/.ros/log/54eb537c-a19f-11e9-a985-68a3c4a1e180/X1-ros1_ign_bridge_twist-5*.log<br />\nprocess[X1/ros1_ign_bridge_camera-6]: started with pid [612]<br />\n/opt/ros/melodic/lib/ros1_ign_bridge/parameter_bridge: symbol lookup error: /opt/ros/melodic/lib/ros1_ign_bridge/parameter_bridge: undefined symbol: _ZN8ignition4msgs8Odometry17default_instance_E<br />\n[X1/ros1_ign_bridge_camera-6] process has died [pid 612, exit code 127, cmd /opt/ros/melodic/lib/ros1_ign_bridge/parameter_bridge /world/tunnel_qual_ign/model/X1/link/base_link/sensor/camera_front/image@sensor_msgs/Image@ignition.msgs.Image /world/tunnel_qual_ign/model/X1/link/base_link/sensor/camera_front/camera_info@sensor_msgs/CameraInfo@ignition.msgs.CameraInfo /world/tunnel_qual_ign/model/X1/link/base_link/sensor/camera_front/image:=front/image_raw /world/tunnel_qual_ign/model/X1/link/base_link/sensor/camera_front/camera_info:=front/camera_info __name:=ros1_ign_bridge_camera __log:=/home/developer/.ros/log/54eb537c-a19f-11e9-a985-68a3c4a1e180/X1-ros1_ign_bridge_camera-6.log].<br />\nlog file: /home/developer/.ros/log/54eb537c-a19f-11e9-a985-68a3c4a1e180/X1-ros1_ign_bridge_camera-6*.log<br />\nprocess[X1/ros1_ign_bridge_gpu_lidar-7]: started with pid [613]<br />\n/opt/ros/melodic/lib/ros1_ign_bridge/parameter_bridge: symbol lookup error: /opt/ros/melodic/lib/ros1_ign_bridge/parameter_bridge: undefined symbol: _ZN8ignition4msgs8Odometry17default_instance_E<br />\n[X1/ros1_ign_bridge_gpu_lidar-7] process has died [pid 613, exit code 127, cmd /opt/ros/melodic/lib/ros1_ign_bridge/parameter_bridge /world/tunnel_qual_ign/model/X1/link/base_link/sensor/front_laser/scan@sensor_msgs/LaserScan@ignition.msgs.LaserScan /world/tunnel_qual_ign/model/X1/link/base_link/sensor/front_laser/scan:=front_scan __name:=ros1_ign_bridge_gpu_lidar __log:=/home/developer/.ros/log/54eb537c-a19f-11e9-a985-68a3c4a1e180/X1-ros1_ign_bridge_gpu_lidar-7.log].<br />\nlog file: /home/developer/.ros/log/54eb537c-a19f-11e9-a985-68a3c4a1e180/X1-ros1_ign_bridge_gpu_lidar-7*.log<br />\nprocess[X1/ros1_ign_bridge_magnetometer-8]: started with pid [614]<br />\n/opt/ros/melodic/lib/ros1_ign_bridge/parameter_bridge: symbol lookup error: /opt/ros/melodic/lib/ros1_ign_bridge/parameter_bridge: undefined symbol: _ZN8ignition4msgs8Odometry17default_instance_E<br />\n[X1/ros1_ign_bridge_magnetometer-8] process has died [pid 614, exit code 127, cmd /opt/ros/melodic/lib/ros1_ign_bridge/parameter_bridge /world/tunnel_qual_ign/model/X1/link/base_link/sensor/magnetometer/magnetometer@sensor_msgs/MagneticField@ignition.msgs.Magnetometer /world/tunnel_qual_ign/model/X1/link/base_link/sensor/magnetometer/magnetometer:=magnetic_field __name:=ros1_ign_bridge_magnetometer __log:=/home/developer/.ros/log/54eb537c-a19f-11e9-a985-68a3c4a1e180/X1-ros1_ign_bridge_magnetometer-8.log].<br />\nlog file: /home/developer/.ros/log/54eb537c-a19f-11e9-a985-68a3c4a1e180/X1-ros1_ign_bridge_magnetometer-8*.log<br />\nprocess[X1/ros1_ign_bridge_fluid_pressure-9]: started with pid [615]<br />\n/opt/ros/melodic/lib/ros1_ign_bridge/parameter_bridge: symbol lookup error: /opt/ros/melodic/lib/ros1_ign_bridge/parameter_bridge: undefined symbol: _ZN8ignition4msgs8Odometry17default_instance_E<br />\n[X1/ros1_ign_bridge_fluid_pressure-9] process has died [pid 615, exit code 127, cmd /opt/ros/melodic/lib/ros1_ign_bridge/parameter_bridge /world/tunnel_qual_ign/model/X1/link/base_link/sensor/air_pressure/air_pressure@sensor_msgs/FluidPressure@ignition.msgs.FluidPressure /world/tunnel_qual_ign/model/X1/link/base_link/sensor/air_pressure/air_pressure:=air_pressure __name:=ros1_ign_bridge_fluid_pressure __log:=/home/developer/.ros/log/54eb537c-a19f-11e9-a985-68a3c4a1e180/X1-ros1_ign_bridge_fluid_pressure-9.log].<br />\nlog file: /home/developer/.ros/log/54eb537c-a19f-11e9-a985-68a3c4a1e180/X1-ros1_ign_bridge_fluid_pressure-9*.log<br />\nprocess[X1/pose_tf_broadcaster-10]: started with pid [616]</p>\n<p>I have highlighted some of the lines. Those lines came in red and simulation came blank.   </p>\n<p><span class=\"ap-mention\" data-atlassian-id=\"5cf75629ff02b50ea27b2817\">@Alfredo Bencomo</span> , <span class=\"ap-mention\" data-atlassian-id=\"557058:095b1e12-74ed-4e20-b44f-2f0745b616e0\">@Nate Koenig</span></p>", "type": "rendered"}, "created_on": "2019-07-08T16:56:12.407813+00:00", "user": {"display_name": "baila", "uuid": "{22c52b82-0467-49e5-afbf-803525a87d06}", "links": {"self": {"href": "https://api.bitbucket.org/2.0/users/%7B22c52b82-0467-49e5-afbf-803525a87d06%7D"}, "html": {"href": "https://bitbucket.org/%7B22c52b82-0467-49e5-afbf-803525a87d06%7D/"}, "avatar": {"href": "data/secure.gravatar.com/avatar/e82780891a1e938f0bf3a529adc858a5d=httpsavatar-management--avatars.us-west-2.prod.public.atl-paas.netinitialsB-3.png"}}, "nickname": "baila", "type": "user", "account_id": "557058:42fc2023-4935-4b2e-8079-075649866124"}, "updated_on": null, "type": "issue_comment", "id": 52896476}