{"links": {"self": {"href": "data/repositories/osrf/subt/issues/299/comments/55315134.json"}, "html": {"href": "#!/osrf/subt/issues/299#comment-55315134"}}, "issue": {"links": {"self": {"href": "data/repositories/osrf/subt/issues/299.json"}}, "type": "issue", "id": 299, "repository": {"links": {"self": {"href": "data/repositories/osrf/subt.json"}, "html": {"href": "#!/osrf/subt"}, "avatar": {"href": "data/bytebucket.org/ravatar/{3c95f6ad-c304-407c-b838-09597d836552}ts=2272898"}}, "type": "repository", "name": "subt", "full_name": "osrf/subt", "uuid": "{3c95f6ad-c304-407c-b838-09597d836552}"}, "title": "Gap in urban_circuit_practice_2"}, "content": {"raw": "Derek, are you testing using a `catkin` workspace or Docker image\\(s\\)?", "markup": "markdown", "html": "<p>Derek, are you testing using a <code>catkin</code> workspace or Docker image(s)?</p>", "type": "rendered"}, "created_on": "2019-12-18T17:50:01.720682+00:00", "user": {"display_name": "Alfredo Bencomo", "uuid": "{84891a71-dff2-4b97-8891-9446c16e6f89}", "links": {"self": {"href": "https://api.bitbucket.org/2.0/users/%7B84891a71-dff2-4b97-8891-9446c16e6f89%7D"}, "html": {"href": "https://bitbucket.org/%7B84891a71-dff2-4b97-8891-9446c16e6f89%7D/"}, "avatar": {"href": "https://avatar-management--avatars.us-west-2.prod.public.atl-paas.net/5cf75629ff02b50ea27b2817/82be1d48-d490-4d7b-8ddb-a8093b9417a6/128"}}, "nickname": "bencomo", "type": "user", "account_id": "5cf75629ff02b50ea27b2817"}, "updated_on": null, "type": "issue_comment", "id": 55315134}