{"pagelen": 50, "values": [{"comment": {"links": {"self": {"href": "data/repositories/osrf/subt/pullrequests/344/comments/126060304.json"}, "html": {"href": "#!/osrf/subt/pull-requests/344/_/diff#comment-126060304"}}, "parent": {"id": 126059966, "links": {"self": {"href": "data/repositories/osrf/subt/pullrequests/344/comments/126059966.json"}, "html": {"href": "#!/osrf/subt/pull-requests/344/_/diff#comment-126059966"}}}, "deleted": false, "pullrequest": {"type": "pullrequest", "id": 344, "links": {"self": {"href": "data/repositories/osrf/subt/pullrequests/344.json"}, "html": {"href": "#!/osrf/subt/pull-requests/344"}}, "title": "Urban practice 03 artifacts"}, "content": {"raw": "Ok, this has been merged into your branch.  We will merge yours once light and gas emitter have been added to `03` as artifacts.", "markup": "markdown", "html": "<p>Ok, this has been merged into your branch.  We will merge yours once light and gas emitter have been added to <code>03</code> as artifacts.</p>", "type": "rendered"}, "created_on": "2019-11-24T03:13:40.524345+00:00", "user": {"display_name": "Alfredo Bencomo", "uuid": "{84891a71-dff2-4b97-8891-9446c16e6f89}", "links": {"self": {"href": "https://api.bitbucket.org/2.0/users/%7B84891a71-dff2-4b97-8891-9446c16e6f89%7D"}, "html": {"href": "https://bitbucket.org/%7B84891a71-dff2-4b97-8891-9446c16e6f89%7D/"}, "avatar": {"href": "https://avatar-management--avatars.us-west-2.prod.public.atl-paas.net/5cf75629ff02b50ea27b2817/82be1d48-d490-4d7b-8ddb-a8093b9417a6/128"}}, "nickname": "bencomo", "type": "user", "account_id": "5cf75629ff02b50ea27b2817"}, "updated_on": "2019-11-24T03:13:40.536288+00:00", "type": "pullrequest_comment", "id": 126060304}, "pull_request": {"type": "pullrequest", "id": 344, "links": {"self": {"href": "data/repositories/osrf/subt/pullrequests/344.json"}, "html": {"href": "#!/osrf/subt/pull-requests/344"}}, "title": "Urban practice 03 artifacts"}}, {"update": {"description": "Add artifacts except light and gas emitter", "title": "Urban practice 03 artifacts", "destination": {"commit": {"hash": "504b062f8c74", "type": "commit", "links": {"self": {"href": "data/repositories/osrf/subt/commit/504b062f8c74.json"}, "html": {"href": "#!/osrf/subt/commits/504b062f8c74"}}}, "repository": {"links": {"self": {"href": "data/repositories/osrf/subt.json"}, "html": {"href": "#!/osrf/subt"}, "avatar": {"href": "data/bytebucket.org/ravatar/{3c95f6ad-c304-407c-b838-09597d836552}ts=2272898"}}, "type": "repository", "name": "subt", "full_name": "osrf/subt", "uuid": "{3c95f6ad-c304-407c-b838-09597d836552}"}, "branch": {"name": "urban_practice_03"}}, "reason": "", "source": {"commit": {"hash": "7688723c729a", "type": "commit", "links": {"self": {"href": "data/repositories/osrf/subt/commit/7688723c729a.json"}, "html": {"href": "#!/osrf/subt/commits/7688723c729a"}}}, "repository": {"links": {"self": {"href": "data/repositories/osrf/subt.json"}, "html": {"href": "#!/osrf/subt"}, "avatar": {"href": "data/bytebucket.org/ravatar/{3c95f6ad-c304-407c-b838-09597d836552}ts=2272898"}}, "type": "repository", "name": "subt", "full_name": "osrf/subt", "uuid": "{3c95f6ad-c304-407c-b838-09597d836552}"}, "branch": {"name": "urban_practice_03_artifacts"}}, "state": "MERGED", "author": {"display_name": "Alfredo Bencomo", "uuid": "{84891a71-dff2-4b97-8891-9446c16e6f89}", "links": {"self": {"href": "https://api.bitbucket.org/2.0/users/%7B84891a71-dff2-4b97-8891-9446c16e6f89%7D"}, "html": {"href": "https://bitbucket.org/%7B84891a71-dff2-4b97-8891-9446c16e6f89%7D/"}, "avatar": {"href": "https://avatar-management--avatars.us-west-2.prod.public.atl-paas.net/5cf75629ff02b50ea27b2817/82be1d48-d490-4d7b-8ddb-a8093b9417a6/128"}}, "nickname": "bencomo", "type": "user", "account_id": "5cf75629ff02b50ea27b2817"}, "date": "2019-11-24T03:12:20.463458+00:00"}, "pull_request": {"type": "pullrequest", "id": 344, "links": {"self": {"href": "data/repositories/osrf/subt/pullrequests/344.json"}, "html": {"href": "#!/osrf/subt/pull-requests/344"}}, "title": "Urban practice 03 artifacts"}}, {"comment": {"links": {"self": {"href": "data/repositories/osrf/subt/pullrequests/344/comments/126059966.json"}, "html": {"href": "#!/osrf/subt/pull-requests/344/_/diff#comment-126059966"}}, "parent": {"id": 126050466, "links": {"self": {"href": "data/repositories/osrf/subt/pullrequests/344/comments/126050466.json"}, "html": {"href": "#!/osrf/subt/pull-requests/344/_/diff#comment-126050466"}}}, "deleted": false, "pullrequest": {"type": "pullrequest", "id": 344, "links": {"self": {"href": "data/repositories/osrf/subt/pullrequests/344.json"}, "html": {"href": "#!/osrf/subt/pull-requests/344"}}, "title": "Urban practice 03 artifacts"}, "content": {"raw": "either way works. We can try get this merged in first before merging pull request #346?", "markup": "markdown", "html": "<p>either way works. We can try get this merged in first before merging <a href=\"#!/osrf/subt/pull-requests/346/add-urban-circuit-practice-03-world\" rel=\"nofollow\" class=\"ap-connect-link\">pull request #346</a>?</p>", "type": "rendered"}, "created_on": "2019-11-24T01:34:11.047467+00:00", "user": {"display_name": "Ian Chen", "uuid": "{eaa6fca5-6deb-43f6-907f-971c144735dd}", "links": {"self": {"href": "https://api.bitbucket.org/2.0/users/%7Beaa6fca5-6deb-43f6-907f-971c144735dd%7D"}, "html": {"href": "https://bitbucket.org/%7Beaa6fca5-6deb-43f6-907f-971c144735dd%7D/"}, "avatar": {"href": "https://avatar-management--avatars.us-west-2.prod.public.atl-paas.net/557058:10b01d41-a2e9-4a41-a907-e6e2f03b6cd5/1e4adcdf-1946-4280-9aea-eb5f15a7f912/128"}}, "nickname": "Ian Chen", "type": "user", "account_id": "557058:10b01d41-a2e9-4a41-a907-e6e2f03b6cd5"}, "updated_on": "2019-11-24T01:34:11.054102+00:00", "type": "pullrequest_comment", "id": 126059966}, "pull_request": {"type": "pullrequest", "id": 344, "links": {"self": {"href": "data/repositories/osrf/subt/pullrequests/344.json"}, "html": {"href": "#!/osrf/subt/pull-requests/344"}}, "title": "Urban practice 03 artifacts"}}, {"comment": {"links": {"self": {"href": "data/repositories/osrf/subt/pullrequests/344/comments/126050466.json"}, "html": {"href": "#!/osrf/subt/pull-requests/344/_/diff#comment-126050466"}}, "deleted": false, "pullrequest": {"type": "pullrequest", "id": 344, "links": {"self": {"href": "data/repositories/osrf/subt/pullrequests/344.json"}, "html": {"href": "#!/osrf/subt/pull-requests/344"}}, "title": "Urban practice 03 artifacts"}, "content": {"raw": "@{557058:10b01d41-a2e9-4a41-a907-e6e2f03b6cd5} should this be merged into your branch first before we merge your other [PR-346](#!/osrf/subt/pull-requests/346) into the `urban_circuit` branch?  \n  \nOR should we merge yours [PR-346](#!/osrf/subt/pull-requests/346) first and change this one to point into the `urban_circuit` branch instead of the `urban_practice_03`?", "markup": "markdown", "html": "<p><span class=\"ap-mention\" data-atlassian-id=\"557058:10b01d41-a2e9-4a41-a907-e6e2f03b6cd5\">@Ian Chen</span> should this be merged into your branch first before we merge your other <a data-is-external-link=\"true\" href=\"#!/osrf/subt/pull-requests/346\" rel=\"nofollow\">PR-346</a> into the <code>urban_circuit</code> branch?  </p>\n<p>OR should we merge yours <a data-is-external-link=\"true\" href=\"#!/osrf/subt/pull-requests/346\" rel=\"nofollow\">PR-346</a> first and change this one to point into the <code>urban_circuit</code> branch instead of the <code>urban_practice_03</code>?</p>", "type": "rendered"}, "created_on": "2019-11-23T03:45:45.970379+00:00", "user": {"display_name": "Alfredo Bencomo", "uuid": "{84891a71-dff2-4b97-8891-9446c16e6f89}", "links": {"self": {"href": "https://api.bitbucket.org/2.0/users/%7B84891a71-dff2-4b97-8891-9446c16e6f89%7D"}, "html": {"href": "https://bitbucket.org/%7B84891a71-dff2-4b97-8891-9446c16e6f89%7D/"}, "avatar": {"href": "https://avatar-management--avatars.us-west-2.prod.public.atl-paas.net/5cf75629ff02b50ea27b2817/82be1d48-d490-4d7b-8ddb-a8093b9417a6/128"}}, "nickname": "bencomo", "type": "user", "account_id": "5cf75629ff02b50ea27b2817"}, "updated_on": "2019-11-23T03:48:54.697551+00:00", "type": "pullrequest_comment", "id": 126050466}, "pull_request": {"type": "pullrequest", "id": 344, "links": {"self": {"href": "data/repositories/osrf/subt/pullrequests/344.json"}, "html": {"href": "#!/osrf/subt/pull-requests/344"}}, "title": "Urban practice 03 artifacts"}}, {"update": {"description": "Add artifacts except light and gas emitter", "title": "Urban practice 03 artifacts", "destination": {"commit": {"hash": "139b08453211", "type": "commit", "links": {"self": {"href": "data/repositories/osrf/subt/commit/139b08453211.json"}, "html": {"href": "#!/osrf/subt/commits/139b08453211"}}}, "repository": {"links": {"self": {"href": "data/repositories/osrf/subt.json"}, "html": {"href": "#!/osrf/subt"}, "avatar": {"href": "data/bytebucket.org/ravatar/{3c95f6ad-c304-407c-b838-09597d836552}ts=2272898"}}, "type": "repository", "name": "subt", "full_name": "osrf/subt", "uuid": "{3c95f6ad-c304-407c-b838-09597d836552}"}, "branch": {"name": "urban_practice_03"}}, "reason": "", "source": {"commit": {"hash": "7688723c729a", "type": "commit", "links": {"self": {"href": "data/repositories/osrf/subt/commit/7688723c729a.json"}, "html": {"href": "#!/osrf/subt/commits/7688723c729a"}}}, "repository": {"links": {"self": {"href": "data/repositories/osrf/subt.json"}, "html": {"href": "#!/osrf/subt"}, "avatar": {"href": "data/bytebucket.org/ravatar/{3c95f6ad-c304-407c-b838-09597d836552}ts=2272898"}}, "type": "repository", "name": "subt", "full_name": "osrf/subt", "uuid": "{3c95f6ad-c304-407c-b838-09597d836552}"}, "branch": {"name": "urban_practice_03_artifacts"}}, "state": "OPEN", "author": {"display_name": "Mabel Zhang", "uuid": "{4b0e38fb-bf50-45c0-a496-61147518b2bf}", "links": {"self": {"href": "https://api.bitbucket.org/2.0/users/%7B4b0e38fb-bf50-45c0-a496-61147518b2bf%7D"}, "html": {"href": "https://bitbucket.org/%7B4b0e38fb-bf50-45c0-a496-61147518b2bf%7D/"}, "avatar": {"href": "https://avatar-management--avatars.us-west-2.prod.public.atl-paas.net/557058:ceb5942c-6843-408c-8550-3ce4899d299b/4d48e5ea-cf28-4fa7-9715-8fc9e315d831/128"}}, "nickname": "mabelmzhang", "type": "user", "account_id": "557058:ceb5942c-6843-408c-8550-3ce4899d299b"}, "date": "2019-11-23T01:00:00.831925+00:00"}, "pull_request": {"type": "pullrequest", "id": 344, "links": {"self": {"href": "data/repositories/osrf/subt/pullrequests/344.json"}, "html": {"href": "#!/osrf/subt/pull-requests/344"}}, "title": "Urban practice 03 artifacts"}}, {"update": {"description": "Add artifacts except light and gas emitter", "title": "Urban practice 03 artifacts", "destination": {"commit": {"hash": "139b08453211", "type": "commit", "links": {"self": {"href": "data/repositories/osrf/subt/commit/139b08453211.json"}, "html": {"href": "#!/osrf/subt/commits/139b08453211"}}}, "repository": {"links": {"self": {"href": "data/repositories/osrf/subt.json"}, "html": {"href": "#!/osrf/subt"}, "avatar": {"href": "data/bytebucket.org/ravatar/{3c95f6ad-c304-407c-b838-09597d836552}ts=2272898"}}, "type": "repository", "name": "subt", "full_name": "osrf/subt", "uuid": "{3c95f6ad-c304-407c-b838-09597d836552}"}, "branch": {"name": "urban_practice_03"}}, "reason": "", "source": {"commit": {"hash": "7688723c729a", "type": "commit", "links": {"self": {"href": "data/repositories/osrf/subt/commit/7688723c729a.json"}, "html": {"href": "#!/osrf/subt/commits/7688723c729a"}}}, "repository": {"links": {"self": {"href": "data/repositories/osrf/subt.json"}, "html": {"href": "#!/osrf/subt"}, "avatar": {"href": "data/bytebucket.org/ravatar/{3c95f6ad-c304-407c-b838-09597d836552}ts=2272898"}}, "type": "repository", "name": "subt", "full_name": "osrf/subt", "uuid": "{3c95f6ad-c304-407c-b838-09597d836552}"}, "branch": {"name": "urban_practice_03_artifacts"}}, "state": "OPEN", "author": {"display_name": "Mabel Zhang", "uuid": "{4b0e38fb-bf50-45c0-a496-61147518b2bf}", "links": {"self": {"href": "https://api.bitbucket.org/2.0/users/%7B4b0e38fb-bf50-45c0-a496-61147518b2bf%7D"}, "html": {"href": "https://bitbucket.org/%7B4b0e38fb-bf50-45c0-a496-61147518b2bf%7D/"}, "avatar": {"href": "https://avatar-management--avatars.us-west-2.prod.public.atl-paas.net/557058:ceb5942c-6843-408c-8550-3ce4899d299b/4d48e5ea-cf28-4fa7-9715-8fc9e315d831/128"}}, "nickname": "mabelmzhang", "type": "user", "account_id": "557058:ceb5942c-6843-408c-8550-3ce4899d299b"}, "date": "2019-11-23T01:00:00.766281+00:00"}, "pull_request": {"type": "pullrequest", "id": 344, "links": {"self": {"href": "data/repositories/osrf/subt/pullrequests/344.json"}, "html": {"href": "#!/osrf/subt/pull-requests/344"}}, "title": "Urban practice 03 artifacts"}}]}