{"links": {"self": {"href": "data/repositories/osrf/subt/issues/242/comments/54277431.json"}, "html": {"href": "#!/osrf/subt/issues/242#comment-54277431"}}, "issue": {"links": {"self": {"href": "data/repositories/osrf/subt/issues/242.json"}}, "type": "issue", "id": 242, "repository": {"links": {"self": {"href": "data/repositories/osrf/subt.json"}, "html": {"href": "#!/osrf/subt"}, "avatar": {"href": "data/bytebucket.org/ravatar/{3c95f6ad-c304-407c-b838-09597d836552}ts=2272898"}}, "type": "repository", "name": "subt", "full_name": "osrf/subt", "uuid": "{3c95f6ad-c304-407c-b838-09597d836552}"}, "title": "Download generated files after upgrade"}, "content": {"raw": "In may case \\(so far one sample, i.e. not representative\\) IT IS MUCH WORSE! Two of four log files cannot be downloaded and the first `rosout.log` ends at 119s when the robot even enter the tunnel yet!\n\n\\`119.076000000 INFO /subt\\_solution \\[/home/developer/subt\\_solution/src/subt\\_seed/src/subt\\_seed\\_node.cc:94\\(imageCallback\\)\\] \\[topics: \\] received Image 1200\n\n\\`17 hours of waiting for this result?!\n\n\u200c", "markup": "markdown", "html": "<p>In may case (so far one sample, i.e. not representative) IT IS MUCH WORSE! Two of four log files cannot be downloaded and the first <code>rosout.log</code> ends at 119s when the robot even enter the tunnel yet!</p>\n<p>`119.<a href=\"#!/osrf/subt/commits/076000000\" rel=\"nofollow\" class=\"ap-connect-link\">076000000</a> INFO /subt_solution [/home/developer/subt_solution/src/subt_seed/src/subt_seed_node.cc:94(imageCallback)] [topics: ] received Image 1200</p>\n<p>`17 hours of waiting for this result?!</p>\n<p>\u200c</p>", "type": "rendered"}, "created_on": "2019-10-09T15:48:28.711559+00:00", "user": {"display_name": "Martin Dlouhy", "uuid": "{27de76db-249c-44be-9eb8-91a3b17bf0d7}", "links": {"self": {"href": "https://api.bitbucket.org/2.0/users/%7B27de76db-249c-44be-9eb8-91a3b17bf0d7%7D"}, "html": {"href": "https://bitbucket.org/%7B27de76db-249c-44be-9eb8-91a3b17bf0d7%7D/"}, "avatar": {"href": "data/secure.gravatar.com/avatar/85a9b1d43839b393296feb3b35a2e577d=httpsavatar-management--avatars.us-west-2.prod.public.atl-paas.netinitialsMD-1.png"}}, "nickname": "robotikacz", "type": "user", "account_id": "557058:490c665b-b69c-40f3-80ea-64f20747efc4"}, "updated_on": null, "type": "issue_comment", "id": 54277431}